setup.py
distributions_OK/Binomialdistribution.py
distributions_OK/Gaussiandistribution.py
distributions_OK/Generaldistribution.py
distributions_OK/__init__.py
distributions_OK.egg-info/PKG-INFO
distributions_OK.egg-info/SOURCES.txt
distributions_OK.egg-info/dependency_links.txt
distributions_OK.egg-info/not-zip-safe
distributions_OK.egg-info/top_level.txt